Metadata-Version: 1.0
Name: gsdistro
Version: 0.1
Summary: Xple distributions
Home-page: UNKNOWN
Author: UNKNOWN
Author-email: UNKNOWN
License: UNKNOWN
Platform: UNKNOWN
